myscop/__init__.py
myscop-0.0.8.dist-info/LICENSE
myscop-0.0.8.dist-info/WHEEL
myscop-0.0.8.dist-info/METADATA
myscop-0.0.8.dist-info/RECORD
