Metadata-Version: 2.1
Name: myscop
Version: 0.0.8
Summary: SCOP is Solver for COnstraint Programing.
Home-page: https://github.com/SaitoTsutomu/myscop
License: MIT
Author: Saito Tsutomu
Author-email: tsutomu7@hotmail.co.jp
Requires-Python: >=3.8,<4.0
Classifier: Development Status :: 1 - Planning
Classifier: License :: OSI Approved :: MIT License
Classifier: Programming Language :: Python
Classifier: Programming Language :: Python :: 3
Classifier: Programming Language :: Python :: 3.8
Classifier: Programming Language :: Python :: 3.9
Classifier: Topic :: Scientific/Engineering
Classifier: Topic :: Software Development
Requires-Dist: more-itertools (>=8.6.0,<9.0.0)
